gpm_precipitation_tools/Add_forecast.py
gpm_precipitation_tools/General_functions.py
gpm_precipitation_tools/Login_UI.py
gpm_precipitation_tools/PPT_CMD_RUN.py
gpm_precipitation_tools/PPT_UI_RUN.py
gpm_precipitation_tools/__init__.py
gpm_precipitation_tools/cli.py
gpm_precipitation_tools/gpm_download_30min_V06B.py
gpm_precipitation_tools/gpm_download_day_V06B.py
gpm_precipitation_tools/gpm_download_month_V06B.py
gpm_precipitation_tools/image_process.py
gpm_precipitation_tools/process_timeseries_files_pipeline.py
gpm_precipitation_tools-0.4.7.dist-info/AUTHORS.rst
gpm_precipitation_tools-0.4.7.dist-info/LICENSE
gpm_precipitation_tools-0.4.7.dist-info/METADATA
gpm_precipitation_tools-0.4.7.dist-info/WHEEL
gpm_precipitation_tools-0.4.7.dist-info/entry_points.txt
gpm_precipitation_tools-0.4.7.dist-info/top_level.txt
gpm_precipitation_tools-0.4.7.dist-info/RECORD
