Metadata-Version: 2.1
Name: gpm_precipitation_tools
Version: 0.4.7
Summary: Package for downloading and analysing NASA Global Precipitation Measurement mission data.
Home-page: https://github.com/LSDtopotools/gpm_precipitation_tools
Author: Marina Ruiz Sanchez-Oro
Author-email: marina.ruiz.so@ed.ac.uk
License: MIT license
Keywords: gpm_precipitation_tools
Platform: UNKNOWN
Classifier: Development Status :: 2 - Pre-Alpha
Classifier: Intended Audience :: Developers
Classifier: License :: OSI Approved :: MIT License
Classifier: Natural Language :: English
Classifier: Programming Language :: Python :: 3
Classifier: Programming Language :: Python :: 3.6
Classifier: Programming Language :: Python :: 3.7
Classifier: Programming Language :: Python :: 3.8
Requires-Python: >=3.6
License-File: LICENSE
License-File: AUTHORS.rst
